celery_state.cpython-35m-x86_64-linux-gnu.so
prometheus_celery_exporter/__init__.py
prometheus_celery_exporter/__main__.py
prometheus_celery_exporter/core.py
prometheus_celery_exporter/metrics.py
prometheus_celery_exporter/monitor.py
prometheus_celery_exporter/utils.py
prometheus_celery_exporter-1.5.0.dist-info/METADATA
prometheus_celery_exporter-1.5.0.dist-info/WHEEL
prometheus_celery_exporter-1.5.0.dist-info/entry_points.txt
prometheus_celery_exporter-1.5.0.dist-info/top_level.txt
prometheus_celery_exporter-1.5.0.dist-info/RECORD
