Metadata-Version: 2.1
Name: prometheus-celery-exporter
Version: 1.5.0
Summary: Prometheus metrics exporter for Celery
Home-page: https://github.com/OvalMoney/celery-exporter
Author: Fabio Todaro, Nicola Martino
Author-email: fbregist@gmail.com, mroci@bruttocarattere.org
License: MIT
Platform: UNKNOWN
Classifier: Development Status :: 3 - Alpha
Classifier: Environment :: Console
Classifier: License :: OSI Approved :: MIT License
Classifier: Programming Language :: Python :: 3.5
Classifier: Programming Language :: Python :: 3 :: Only
Classifier: Operating System :: OS Independent
Requires-Dist: click (>=7)
Requires-Dist: celery (>=4)
Requires-Dist: prometheus-client (>=0.0.20)
